CHANGES.txt
README.txt
setup.cfg
setup.py
docs/HISTORY.txt
docs/INSTALL.txt
docs/LICENSE.GPL
docs/LICENSE.txt
zgeo/__init__.py
zgeo.plone.atom.egg-info/PKG-INFO
zgeo.plone.atom.egg-info/SOURCES.txt
zgeo.plone.atom.egg-info/dependency_links.txt
zgeo.plone.atom.egg-info/entry_points.txt
zgeo.plone.atom.egg-info/namespace_packages.txt
zgeo.plone.atom.egg-info/not-zip-safe
zgeo.plone.atom.egg-info/requires.txt
zgeo.plone.atom.egg-info/top_level.txt
zgeo/plone/__init__.py
zgeo/plone/atom/README.txt
zgeo/plone/atom/__init__.py
zgeo/plone/atom/browser.py
zgeo/plone/atom/configure.zcml
zgeo/plone/atom/setuphandlers.py
zgeo/plone/atom/version.txt
zgeo/plone/atom/Extensions/Install.py
zgeo/plone/atom/Extensions/__init__.py
zgeo/plone/atom/profiles/default/import_steps.xml
zgeo/plone/atom/profiles/default/zgeo.plone.atom_various.txt
zgeo/plone/atom/tests/__init__.py
zgeo/plone/atom/tests/atom-docs.txt
zgeo/plone/atom/tests/base.py
zgeo/plone/atom/tests/large-folder-atom.txt
zgeo/plone/atom/tests/test_doctests.py
zgeo/plone/atom/tests/test_setup.py
