Metadata-Version: 1.0
Name: zgeo.plone.atom
Version: 0.2
Summary: Plone specific Atom syndication with GeoRSS
Home-page: http://trac.gispython.org/projects/PrimaGIS/wiki/zgeo.plone.atom
Author: Sean Gillies
Author-email: sgillies@frii.com
License: GPL
Keywords: plone geo gis georss atom
Platform: UNKNOWN
Classifier: Framework :: Plone
Classifier: Framework :: Zope2
Classifier: Framework :: Zope3
Classifier: Programming Language :: Python
Classifier: Topic :: Software Development :: Libraries :: Python Modules
Classifier: Topic :: Scientific/Engineering :: GIS
Classifier: Development Status :: 3 - Alpha
Classifier: Intended Audience :: Developers
